Metadata-Version: 1.0
Name: soogang
Version: 0.0.1.9
Summary: soogang sdk
Home-page: https://github.com/sougang/soogang-sdk
Author: Ryan Wang
Author-email: hwwangwang@gmail.com
License: MIT
Platform: UNKNOWN
